{
  "id": "insonia_apneia",
  "queixa": "insonia",
  "nome": "Sindrome da Apneia Obstrutiva do Sono",
  "cid10": "G47.33",
  "versao": "1.0",
  "prevalencia": { "masculino_adulto": 15, "feminino_adulto": 8, "obesidade": 40 },
  "criterios_positivos": [
    { "campo": "sintomas_associados", "operador": "contains_any", "valor": ["ronco", "ronca alto", "engasgo sono", "parada respiracao"], "peso": 5 },
    { "campo": "sintomas_associados", "operador": "contains_any", "valor": ["sono nao reparador", "cansaco dia", "sonolencia diurna"], "peso": 5 },
    { "campo": "habitos", "operador": "contains_any", "valor": ["dormindo direcao", "acidente sonolencia"], "peso": 5 },
    { "campo": "condicoes_mencionadas", "operador": "contains_any", "valor": ["obesidade", "has", "diabetes"], "peso": 3 }
  ],
  "modificadores_demograficos": [
    { "condicao": "sexo==masculino && idade>=40", "peso_extra": 2 }
  ],
  "fatores_risco": ["obesidade", "pescoco_largo", "alteracao_craniofacial", "tabagismo", "etilismo"],
  "exames_relevantes": ["polissonografia", "escala_epworth"],
  "proximo_passo_template": "Escala de Epworth. Polissonografia (padrao ouro) ou poligrafia respiratoria. CPAP e tratamento de escolha em AOS moderada-grave. Perda de peso se obeso. Evitar alcool, benzodiazepinico, dormir em decubito dorsal.",
  "fonte": { "titulo": "ABS + SBPT — Consenso AOS", "ano": 2022, "prioridade": 1, "tipo": "diretriz_sociedade_medica_br" },
  "nivel_evidencia": "A"
}
